{
  "app.js": "/TechJournal/static/js/app.b6a39c4e.js",
  "app.js.map": "/TechJournal/static/js/app.3071709cc3fef358947c.js.map",
  "index.js": "/TechJournal/static/js/index.07a46fd8.js",
  "index.js.map": "/TechJournal/static/js/index.3071709cc3fef358947c.js.map",
  "runtime~app.js": "/TechJournal/static/js/runtime~app.3071709cc3fef358947c.js",
  "runtime~app.js.map": "/TechJournal/static/js/runtime~app.3071709cc3fef358947c.js.map",
  "vendors.js": "/TechJournal/static/js/vendors.c054613e.js",
  "vendors.js.map": "/TechJournal/static/js/vendors.3071709cc3fef358947c.js.map",
  "static/js/4.f5a0c64e.js": "/TechJournal/static/js/4.f5a0c64e.js",
  "static/js/4.3071709cc3fef358947c.js.map": "/TechJournal/static/js/4.3071709cc3fef358947c.js.map",
  "index.html": "/TechJournal/index.html"
}